mcp_rocq/__init__.py
mcp_rocq/__main__.py
mcp_rocq/cli.py
mcp_rocq/patch.py
mcp_rocq/server.py
mcp_rocq/handlers/__init__.py
mcp_rocq/handlers/coq_session.py
mcp_rocq/handlers/inductive_types.py
mcp_rocq/handlers/prover.py
mcp_rocq/handlers/type_checker.py
mcp_rocq/parsers/xml_parser.py
mseep_mcp_rocq-0.1.1.dist-info/METADATA
mseep_mcp_rocq-0.1.1.dist-info/WHEEL
mseep_mcp_rocq-0.1.1.dist-info/entry_points.txt
mseep_mcp_rocq-0.1.1.dist-info/licenses/LICENSE
mseep_mcp_rocq-0.1.1.dist-info/RECORD
